sb_async_cryptography/__init__.py
sb_async_cryptography/keys_generation.py
sb_async_cryptography/sberbank_tools.py
sb_async_cryptography/signature.py
sberbank_async_cryptography-1.0.0.dist-info/METADATA
sberbank_async_cryptography-1.0.0.dist-info/WHEEL
sberbank_async_cryptography-1.0.0.dist-info/top_level.txt
sberbank_async_cryptography-1.0.0.dist-info/RECORD
