Metadata-Version: 2.1
Name: sberbank-async-cryptography
Version: 1.0.0
Summary: Python implementation of Sberbank signature verification (using async cryptography).
Home-page: https://github.com/egorgvo/sberbank_callback_async_cryptography
Author: Egor Gvo
Author-email: work.egvo@ya.ru
License: MIT
Platform: UNKNOWN
Classifier: License :: OSI Approved :: MIT License
Classifier: Programming Language :: Python :: 3
Requires-Dist: pycryptodomex (==3.9.8)
Requires-Dist: cryptography (==3.0)
